[
	{
		"__TYPE__": "SharedSliceContent",
		"variation": "default",
		"primary": {
			"imagem_de_fundo_herosection_web": {
				"origin": {
					"id": "main",
					"url": "https://images.unsplash.com/photo-1537498425277-c283d32ef9db",
					"width": 4380,
					"height": 2895
				},
				"url": "https://images.unsplash.com/photo-1537498425277-c283d32ef9db",
				"width": 4380,
				"height": 2895,
				"edit": {
					"zoom": 1,
					"crop": {
						"x": 0,
						"y": 0
					},
					"background": "transparent"
				},
				"credits": null,
				"alt": null,
				"__TYPE__": "ImageContent",
				"thumbnails": {}
			},
			"imagem_de_fundo_herosection_mobile": {
				"origin": {
					"id": "main",
					"url": "https://images.unsplash.com/photo-1589321599763-d66926c29613",
					"width": 3168,
					"height": 4752
				},
				"url": "https://images.unsplash.com/photo-1589321599763-d66926c29613",
				"width": 3168,
				"height": 4752,
				"edit": {
					"zoom": 1,
					"crop": {
						"x": 0,
						"y": 0
					},
					"background": "transparent"
				},
				"credits": null,
				"alt": null,
				"__TYPE__": "ImageContent",
				"thumbnails": {}
			},
			"textoprincipal": {
				"__TYPE__": "FieldContent",
				"value": "they",
				"type": "Text"
			},
			"whatsapp": {
				"__TYPE__": "FieldContent",
				"value": "twice",
				"type": "Text"
			},
			"texto_para_falar_do_lugar": {
				"__TYPE__": "StructuredTextContent",
				"value": [
					{
						"type": "paragraph",
						"content": {
							"text": "Non pariatur est esse. Tempor ex consectetur incididunt qui pariatur ea commodo dolore qui eu voluptate nisi occaecat adipisicing. Pariatur et reprehenderit aliqua elit esse incididunt laborum."
						}
					}
				]
			}
		},
		"items": []
	}
]